{
  "date": "2026-07-16",
  "course": {
    "reunion": "R1",
    "course_num": "C8",
    "hippodrome": "Compiegne",
    "nom": "PRIX DU CHATEAU DE PIERREFONDS",
    "heure": "20h15",
    "type": "PLAT",
    "categorie": "HANDICAP_DIVISE",
    "nb_partants": 16,
    "allocation_eur": 50900,
    "distance_m": 1400,
    "corde": "CORDE_GAUCHE",
    "terrain": "-",
    "meteo": null
  },
  "fiabilite_globale": 1.0,
  "ponderations": {
    "cote": 0.55,
    "gains": 0.03,
    "couple_je": 0.12,
    "hippodrome": 0.1,
    "pref_terrain": 0.12,
    "pref_distance": 0.04,
    "recuperation": 0.04
  },
  "top5": [
    {
      "numero": 6,
      "nom": "My Queen",
      "artifice": null,
      "sexe": "FEMELLES",
      "age": 4,
      "poids": null,
      "jockey": "P.Remoue",
      "musique": "3p6p3p2p(25)2p2p1p0p3p",
      "vh": null,
      "gains_eur": 50501,
      "entraineur": "Pier.Menard",
      "cote_pmu": 62.0,
      "non_partant": false,
      "musique_raw": "3p6p3p2p(25)2p2p1p0p3p",
      "nb_courses_recentes": 9,
      "nb_victoires_recentes": 1,
      "nb_places_recentes": 8,
      "derniere_position": 3,
      "position_moyenne": 2.44,
      "sous_scores": {
        "cote": 0.0135,
        "gains": 0.3419,
        "couple_je": 0.5,
        "hippodrome": 0.5,
        "pref_terrain": 0.8889,
        "pref_distance": 0.8889,
        "recuperation": 0.5
      },
      "score": 28.99,
      "enrichi": false,
      "rang_predit": 4
    },
    {
      "numero": 16,
      "nom": "Tantomile",
      "artifice": null,
      "sexe": "FEMELLES",
      "age": 5,
      "poids": null,
      "jockey": "M.Velon",
      "musique": "0p5p(25)7p2p4p3p4p2p2p",
      "vh": null,
      "gains_eur": 91315,
      "entraineur": "N.Caullery",
      "cote_pmu": 13.0,
      "non_partant": false,
      "musique_raw": "0p5p(25)7p2p4p3p4p2p2p",
      "nb_courses_recentes": 9,
      "nb_victoires_recentes": 0,
      "nb_places_recentes": 5,
      "derniere_position": 0,
      "position_moyenne": 3.22,
      "sous_scores": {
        "cote": 0.0643,
        "gains": 0.6182,
        "couple_je": 0.5,
        "hippodrome": 0.5,
        "pref_terrain": 0.5556,
        "pref_distance": 0.5556,
        "recuperation": 0.5
      },
      "score": 27.28,
      "enrichi": false,
      "rang_predit": 6
    },
    {
      "numero": 9,
      "nom": "Zasymoka",
      "artifice": null,
      "sexe": "FEMELLES",
      "age": 5,
      "poids": null,
      "jockey": "L.Plommee",
      "musique": "3p3p0p1p2p0p(25)0p7p9p",
      "vh": null,
      "gains_eur": 62380,
      "entraineur": "M.Cesandri (S)",
      "cote_pmu": 26.0,
      "non_partant": false,
      "musique_raw": "3p3p0p1p2p0p(25)0p7p9p",
      "nb_courses_recentes": 9,
      "nb_victoires_recentes": 1,
      "nb_places_recentes": 7,
      "derniere_position": 3,
      "position_moyenne": 2.78,
      "sous_scores": {
        "cote": 0.0322,
        "gains": 0.4223,
        "couple_je": 0.5,
        "hippodrome": 0.5,
        "pref_terrain": 0.7778,
        "pref_distance": 0.7778,
        "recuperation": 0.5
      },
      "score": 28.48,
      "enrichi": false,
      "rang_predit": 5
    },
    {
      "numero": 5,
      "nom": "The Shadow",
      "artifice": null,
      "sexe": "FEMELLES",
      "age": 4,
      "poids": null,
      "jockey": "C.Soumillon",
      "musique": "2p2p1p2p4p(25)0p2p3p1p",
      "vh": null,
      "gains_eur": 74155,
      "entraineur": "N.Caullery",
      "cote_pmu": 1.4,
      "non_partant": false,
      "musique_raw": "2p2p1p2p4p(25)0p2p3p1p",
      "nb_courses_recentes": 9,
      "nb_victoires_recentes": 2,
      "nb_places_recentes": 8,
      "derniere_position": 2,
      "position_moyenne": 1.89,
      "sous_scores": {
        "cote": 0.5972,
        "gains": 0.5021,
        "couple_je": 0.5,
        "hippodrome": 0.5,
        "pref_terrain": 0.8889,
        "pref_distance": 0.8889,
        "recuperation": 0.5
      },
      "score": 61.57,
      "enrichi": false,
      "rang_predit": 1
    },
    {
      "numero": 1,
      "nom": "Miss Oxford",
      "artifice": null,
      "sexe": "FEMELLES",
      "age": 5,
      "poids": null,
      "jockey": "F.Valle Skar",
      "musique": "3p0p(25)0p0p1p3p0p0p",
      "vh": null,
      "gains_eur": 45541,
      "entraineur": "S.Kobayashi (S)",
      "cote_pmu": 48.0,
      "non_partant": false,
      "musique_raw": "3p0p(25)0p0p1p3p0p0p",
      "nb_courses_recentes": 8,
      "nb_victoires_recentes": 1,
      "nb_places_recentes": 8,
      "derniere_position": 3,
      "position_moyenne": 0.88,
      "sous_scores": {
        "cote": 0.0174,
        "gains": 0.3083,
        "couple_je": 0.5,
        "hippodrome": 0.5,
        "pref_terrain": 1.0,
        "pref_distance": 1.0,
        "recuperation": 0.5
      },
      "score": 30.88,
      "enrichi": false,
      "rang_predit": 2
    },
    {
      "numero": 13,
      "nom": "Amorcita",
      "artifice": null,
      "sexe": "FEMELLES",
      "age": 5,
      "poids": null,
      "jockey": "A.Molins",
      "musique": "1p0p0p4p0p0p1p(25)0p0p",
      "vh": null,
      "gains_eur": 78362,
      "entraineur": "Ha.Pantall (S)",
      "cote_pmu": 70.0,
      "non_partant": false,
      "musique_raw": "1p0p0p4p0p0p1p(25)0p0p",
      "nb_courses_recentes": 9,
      "nb_victoires_recentes": 2,
      "nb_places_recentes": 8,
      "derniere_position": 1,
      "position_moyenne": 0.67,
      "sous_scores": {
        "cote": 0.0119,
        "gains": 0.5305,
        "couple_je": 0.5,
        "hippodrome": 0.5,
        "pref_terrain": 0.8889,
        "pref_distance": 0.8889,
        "recuperation": 0.5
      },
      "score": 29.47,
      "enrichi": false,
      "rang_predit": 3
    }
  ],
  "tous_chevaux": [
    {
      "numero": 5,
      "nom": "The Shadow",
      "artifice": null,
      "sexe": "FEMELLES",
      "age": 4,
      "poids": null,
      "jockey": "C.Soumillon",
      "musique": "2p2p1p2p4p(25)0p2p3p1p",
      "vh": null,
      "gains_eur": 74155,
      "entraineur": "N.Caullery",
      "cote_pmu": 1.4,
      "non_partant": false,
      "musique_raw": "2p2p1p2p4p(25)0p2p3p1p",
      "nb_courses_recentes": 9,
      "nb_victoires_recentes": 2,
      "nb_places_recentes": 8,
      "derniere_position": 2,
      "position_moyenne": 1.89,
      "sous_scores": {
        "cote": 0.5972,
        "gains": 0.5021,
        "couple_je": 0.5,
        "hippodrome": 0.5,
        "pref_terrain": 0.8889,
        "pref_distance": 0.8889,
        "recuperation": 0.5
      },
      "score": 61.57,
      "enrichi": false,
      "rang_predit": 1
    },
    {
      "numero": 1,
      "nom": "Miss Oxford",
      "artifice": null,
      "sexe": "FEMELLES",
      "age": 5,
      "poids": null,
      "jockey": "F.Valle Skar",
      "musique": "3p0p(25)0p0p1p3p0p0p",
      "vh": null,
      "gains_eur": 45541,
      "entraineur": "S.Kobayashi (S)",
      "cote_pmu": 48.0,
      "non_partant": false,
      "musique_raw": "3p0p(25)0p0p1p3p0p0p",
      "nb_courses_recentes": 8,
      "nb_victoires_recentes": 1,
      "nb_places_recentes": 8,
      "derniere_position": 3,
      "position_moyenne": 0.88,
      "sous_scores": {
        "cote": 0.0174,
        "gains": 0.3083,
        "couple_je": 0.5,
        "hippodrome": 0.5,
        "pref_terrain": 1.0,
        "pref_distance": 1.0,
        "recuperation": 0.5
      },
      "score": 30.88,
      "enrichi": false,
      "rang_predit": 2
    },
    {
      "numero": 13,
      "nom": "Amorcita",
      "artifice": null,
      "sexe": "FEMELLES",
      "age": 5,
      "poids": null,
      "jockey": "A.Molins",
      "musique": "1p0p0p4p0p0p1p(25)0p0p",
      "vh": null,
      "gains_eur": 78362,
      "entraineur": "Ha.Pantall (S)",
      "cote_pmu": 70.0,
      "non_partant": false,
      "musique_raw": "1p0p0p4p0p0p1p(25)0p0p",
      "nb_courses_recentes": 9,
      "nb_victoires_recentes": 2,
      "nb_places_recentes": 8,
      "derniere_position": 1,
      "position_moyenne": 0.67,
      "sous_scores": {
        "cote": 0.0119,
        "gains": 0.5305,
        "couple_je": 0.5,
        "hippodrome": 0.5,
        "pref_terrain": 0.8889,
        "pref_distance": 0.8889,
        "recuperation": 0.5
      },
      "score": 29.47,
      "enrichi": false,
      "rang_predit": 3
    },
    {
      "numero": 6,
      "nom": "My Queen",
      "artifice": null,
      "sexe": "FEMELLES",
      "age": 4,
      "poids": null,
      "jockey": "P.Remoue",
      "musique": "3p6p3p2p(25)2p2p1p0p3p",
      "vh": null,
      "gains_eur": 50501,
      "entraineur": "Pier.Menard",
      "cote_pmu": 62.0,
      "non_partant": false,
      "musique_raw": "3p6p3p2p(25)2p2p1p0p3p",
      "nb_courses_recentes": 9,
      "nb_victoires_recentes": 1,
      "nb_places_recentes": 8,
      "derniere_position": 3,
      "position_moyenne": 2.44,
      "sous_scores": {
        "cote": 0.0135,
        "gains": 0.3419,
        "couple_je": 0.5,
        "hippodrome": 0.5,
        "pref_terrain": 0.8889,
        "pref_distance": 0.8889,
        "recuperation": 0.5
      },
      "score": 28.99,
      "enrichi": false,
      "rang_predit": 4
    },
    {
      "numero": 9,
      "nom": "Zasymoka",
      "artifice": null,
      "sexe": "FEMELLES",
      "age": 5,
      "poids": null,
      "jockey": "L.Plommee",
      "musique": "3p3p0p1p2p0p(25)0p7p9p",
      "vh": null,
      "gains_eur": 62380,
      "entraineur": "M.Cesandri (S)",
      "cote_pmu": 26.0,
      "non_partant": false,
      "musique_raw": "3p3p0p1p2p0p(25)0p7p9p",
      "nb_courses_recentes": 9,
      "nb_victoires_recentes": 1,
      "nb_places_recentes": 7,
      "derniere_position": 3,
      "position_moyenne": 2.78,
      "sous_scores": {
        "cote": 0.0322,
        "gains": 0.4223,
        "couple_je": 0.5,
        "hippodrome": 0.5,
        "pref_terrain": 0.7778,
        "pref_distance": 0.7778,
        "recuperation": 0.5
      },
      "score": 28.48,
      "enrichi": false,
      "rang_predit": 5
    },
    {
      "numero": 16,
      "nom": "Tantomile",
      "artifice": null,
      "sexe": "FEMELLES",
      "age": 5,
      "poids": null,
      "jockey": "M.Velon",
      "musique": "0p5p(25)7p2p4p3p4p2p2p",
      "vh": null,
      "gains_eur": 91315,
      "entraineur": "N.Caullery",
      "cote_pmu": 13.0,
      "non_partant": false,
      "musique_raw": "0p5p(25)7p2p4p3p4p2p2p",
      "nb_courses_recentes": 9,
      "nb_victoires_recentes": 0,
      "nb_places_recentes": 5,
      "derniere_position": 0,
      "position_moyenne": 3.22,
      "sous_scores": {
        "cote": 0.0643,
        "gains": 0.6182,
        "couple_je": 0.5,
        "hippodrome": 0.5,
        "pref_terrain": 0.5556,
        "pref_distance": 0.5556,
        "recuperation": 0.5
      },
      "score": 27.28,
      "enrichi": false,
      "rang_predit": 6
    },
    {
      "numero": 4,
      "nom": "Zakosha",
      "artifice": null,
      "sexe": "FEMELLES",
      "age": 4,
      "poids": null,
      "jockey": "A.Pouchin",
      "musique": "8p0p1p0p1p2p6p(25)4p2p",
      "vh": null,
      "gains_eur": 60883,
      "entraineur": "G.Mosse (S)",
      "cote_pmu": 50.0,
      "non_partant": false,
      "musique_raw": "8p0p1p0p1p2p6p(25)4p2p",
      "nb_courses_recentes": 9,
      "nb_victoires_recentes": 2,
      "nb_places_recentes": 6,
      "derniere_position": 8,
      "position_moyenne": 2.67,
      "sous_scores": {
        "cote": 0.0167,
        "gains": 0.4122,
        "couple_je": 0.5,
        "hippodrome": 0.5,
        "pref_terrain": 0.6667,
        "pref_distance": 0.6667,
        "recuperation": 0.5
      },
      "score": 25.82,
      "enrichi": false,
      "rang_predit": 7
    },
    {
      "numero": 8,
      "nom": "He Touched Me",
      "artifice": null,
      "sexe": "FEMELLES",
      "age": 4,
      "poids": null,
      "jockey": "M.Barzalona",
      "musique": "5p7p0p2p0p(25)1p1p5p6p",
      "vh": null,
      "gains_eur": 48480,
      "entraineur": "G.Bietolini",
      "cote_pmu": 30.0,
      "non_partant": false,
      "musique_raw": "5p7p0p2p0p(25)1p1p5p6p",
      "nb_courses_recentes": 9,
      "nb_victoires_recentes": 2,
      "nb_places_recentes": 5,
      "derniere_position": 5,
      "position_moyenne": 3.0,
      "sous_scores": {
        "cote": 0.0279,
        "gains": 0.3282,
        "couple_je": 0.5,
        "hippodrome": 0.5,
        "pref_terrain": 0.5556,
        "pref_distance": 0.5556,
        "recuperation": 0.5
      },
      "score": 24.41,
      "enrichi": false,
      "rang_predit": 8
    },
    {
      "numero": 2,
      "nom": "Omicrone",
      "artifice": null,
      "sexe": "FEMELLES",
      "age": 6,
      "poids": null,
      "jockey": "C.Lecoeuvre",
      "musique": "8p0p9p0p(25)8p7p4p8p1p",
      "vh": null,
      "gains_eur": 134700,
      "entraineur": "P.Groualle (S)",
      "cote_pmu": 14.0,
      "non_partant": false,
      "musique_raw": "8p0p9p0p(25)8p7p4p8p1p",
      "nb_courses_recentes": 9,
      "nb_victoires_recentes": 1,
      "nb_places_recentes": 3,
      "derniere_position": 8,
      "position_moyenne": 5.0,
      "sous_scores": {
        "cote": 0.0597,
        "gains": 0.912,
        "couple_je": 0.5,
        "hippodrome": 0.5,
        "pref_terrain": 0.3333,
        "pref_distance": 0.3333,
        "recuperation": 0.5
      },
      "score": 24.35,
      "enrichi": false,
      "rang_predit": 9
    },
    {
      "numero": 12,
      "nom": "Best Looking",
      "artifice": null,
      "sexe": "FEMELLES",
      "age": 5,
      "poids": null,
      "jockey": "B.Marie",
      "musique": "6p4p3p1p(25)4p1p0p5p4p",
      "vh": null,
      "gains_eur": 53342,
      "entraineur": "Mme C.Whitfield",
      "cote_pmu": 45.0,
      "non_partant": false,
      "musique_raw": "6p4p3p1p(25)4p1p0p5p4p",
      "nb_courses_recentes": 9,
      "nb_victoires_recentes": 2,
      "nb_places_recentes": 4,
      "derniere_position": 6,
      "position_moyenne": 3.11,
      "sous_scores": {
        "cote": 0.0186,
        "gains": 0.3611,
        "couple_je": 0.5,
        "hippodrome": 0.5,
        "pref_terrain": 0.4444,
        "pref_distance": 0.4444,
        "recuperation": 0.5
      },
      "score": 22.22,
      "enrichi": false,
      "rang_predit": 10
    },
    {
      "numero": 14,
      "nom": "Dark Zel",
      "artifice": null,
      "sexe": "FEMELLES",
      "age": 6,
      "poids": null,
      "jockey": "J.Claudic",
      "musique": "3p0p4p6p3p4p8p4p(25)7p",
      "vh": null,
      "gains_eur": 89277,
      "entraineur": "N.Caullery",
      "cote_pmu": 26.0,
      "non_partant": false,
      "musique_raw": "3p0p4p6p3p4p8p4p(25)7p",
      "nb_courses_recentes": 9,
      "nb_victoires_recentes": 0,
      "nb_places_recentes": 3,
      "derniere_position": 3,
      "position_moyenne": 4.33,
      "sous_scores": {
        "cote": 0.0322,
        "gains": 0.6044,
        "couple_je": 0.5,
        "hippodrome": 0.5,
        "pref_terrain": 0.3333,
        "pref_distance": 0.3333,
        "recuperation": 0.5
      },
      "score": 21.92,
      "enrichi": false,
      "rang_predit": 11
    },
    {
      "numero": 11,
      "nom": "Aversa",
      "artifice": null,
      "sexe": "FEMELLES",
      "age": 6,
      "poids": null,
      "jockey": "E.Hardouin",
      "musique": "8p(25)0p4p9p0p0p4p6p6p",
      "vh": null,
      "gains_eur": 147701,
      "entraineur": "N.Caullery",
      "cote_pmu": 80.0,
      "non_partant": false,
      "musique_raw": "8p(25)0p4p9p0p0p4p6p6p",
      "nb_courses_recentes": 9,
      "nb_victoires_recentes": 0,
      "nb_places_recentes": 3,
      "derniere_position": 8,
      "position_moyenne": 4.11,
      "sous_scores": {
        "cote": 0.0105,
        "gains": 1.0,
        "couple_je": 0.5,
        "hippodrome": 0.5,
        "pref_terrain": 0.3333,
        "pref_distance": 0.3333,
        "recuperation": 0.5
      },
      "score": 21.91,
      "enrichi": false,
      "rang_predit": 12
    },
    {
      "numero": 7,
      "nom": "Victory Folie",
      "artifice": null,
      "sexe": "FEMELLES",
      "age": 4,
      "poids": null,
      "jockey": "S.Pasquier",
      "musique": "8p7p(25)8p2p4p8p2p4p0p",
      "vh": null,
      "gains_eur": 45080,
      "entraineur": "N.Caullery",
      "cote_pmu": 36.0,
      "non_partant": false,
      "musique_raw": "8p7p(25)8p2p4p8p2p4p0p",
      "nb_courses_recentes": 9,
      "nb_victoires_recentes": 0,
      "nb_places_recentes": 3,
      "derniere_position": 8,
      "position_moyenne": 4.78,
      "sous_scores": {
        "cote": 0.0232,
        "gains": 0.3052,
        "couple_je": 0.5,
        "hippodrome": 0.5,
        "pref_terrain": 0.3333,
        "pref_distance": 0.3333,
        "recuperation": 0.5
      },
      "score": 20.53,
      "enrichi": false,
      "rang_predit": 13
    },
    {
      "numero": 10,
      "nom": "Elusive Belardo",
      "artifice": null,
      "sexe": "FEMELLES",
      "age": 4,
      "poids": null,
      "jockey": "T.Trullier",
      "musique": "6p0p4p8p4p(25)0p0p8p4p",
      "vh": null,
      "gains_eur": 46851,
      "entraineur": "N.Caullery",
      "cote_pmu": 50.0,
      "non_partant": false,
      "musique_raw": "6p0p4p8p4p(25)0p0p8p4p",
      "nb_courses_recentes": 9,
      "nb_victoires_recentes": 0,
      "nb_places_recentes": 3,
      "derniere_position": 6,
      "position_moyenne": 3.78,
      "sous_scores": {
        "cote": 0.0167,
        "gains": 0.3172,
        "couple_je": 0.5,
        "hippodrome": 0.5,
        "pref_terrain": 0.3333,
        "pref_distance": 0.3333,
        "recuperation": 0.5
      },
      "score": 20.2,
      "enrichi": false,
      "rang_predit": 14
    },
    {
      "numero": 15,
      "nom": "Placeholder",
      "artifice": null,
      "sexe": "FEMELLES",
      "age": 5,
      "poids": null,
      "jockey": "A.Madamet",
      "musique": "7p4p5p0p(25)9p1p6p5p5p",
      "vh": null,
      "gains_eur": 56624,
      "entraineur": "G.Hernon (S)",
      "cote_pmu": 34.0,
      "non_partant": false,
      "musique_raw": "7p4p5p0p(25)9p1p6p5p5p",
      "nb_courses_recentes": 9,
      "nb_victoires_recentes": 1,
      "nb_places_recentes": 2,
      "derniere_position": 7,
      "position_moyenne": 4.67,
      "sous_scores": {
        "cote": 0.0246,
        "gains": 0.3834,
        "couple_je": 0.5,
        "hippodrome": 0.5,
        "pref_terrain": 0.2222,
        "pref_distance": 0.2222,
        "recuperation": 0.5
      },
      "score": 19.06,
      "enrichi": false,
      "rang_predit": 15
    },
    {
      "numero": 3,
      "nom": "Zawan",
      "artifice": null,
      "sexe": "FEMELLES",
      "age": 4,
      "poids": null,
      "jockey": "C.Demuro",
      "musique": "9p5p9p(25)4p7p6p4p1p9p",
      "vh": null,
      "gains_eur": 39551,
      "entraineur": "G.Hernon (S)",
      "cote_pmu": 25.0,
      "non_partant": false,
      "musique_raw": "9p5p9p(25)4p7p6p4p1p9p",
      "nb_courses_recentes": 9,
      "nb_victoires_recentes": 1,
      "nb_places_recentes": 1,
      "derniere_position": 9,
      "position_moyenne": 6.0,
      "sous_scores": {
        "cote": 0.0334,
        "gains": 0.2678,
        "couple_je": 0.5,
        "hippodrome": 0.5,
        "pref_terrain": 0.1111,
        "pref_distance": 0.1111,
        "recuperation": 0.5
      },
      "score": 17.42,
      "enrichi": false,
      "rang_predit": 16
    }
  ],
  "nb_enrichis": 0,
  "nb_partants": 16,
  "cotes_dispo": 16
}