{
  "date": "2026-06-05",
  "course": {
    "reunion": "R1",
    "course_num": "C4",
    "hippodrome": "Paris-Vincennes",
    "nom": null,
    "heure": "20h15",
    "type": null,
    "categorie": null,
    "nb_partants": 16,
    "allocation_eur": 59000,
    "distance_m": 2100,
    "corde": "gauche",
    "terrain": "-",
    "meteo": "13°C Nuages dispersés, vent 12km/h - O"
  },
  "fiabilite_globale": 1.0,
  "ponderations": {
    "cote": 0.4,
    "gains": 0.15,
    "couple_je": 0.15,
    "hippodrome": 0.1,
    "pref_terrain": 0.1,
    "pref_distance": 0.05,
    "recuperation": 0.05
  },
  "top5": [
    {
      "numero": 4,
      "nom": "Idole Jallerie",
      "artifice": null,
      "sexe": "F",
      "age": 8,
      "poids": 2100.0,
      "jockey": "F. Nivard",
      "musique": "DaDa3a3a1a1a",
      "vh": null,
      "gains_eur": 193375,
      "entraineur": "D. Héon",
      "cote_pmu": 2.1,
      "non_partant": false,
      "musique_raw": "DaDa3a3a1a1a",
      "nb_courses_recentes": 6,
      "nb_victoires_recentes": 2,
      "nb_places_recentes": 4,
      "derniere_position": 3,
      "position_moyenne": 2.0,
      "fiche_enrichie": {
        "numero": 4,
        "nom": "Idole Jallerie",
        "carte_identite": {
          "jockey": "Éleveur",
          "entraineur": "F. Nivard",
          "proprietaire": "D. Héon",
          "eleveur": "D. Héon",
          "sexe": "Discipline",
          "robe": "Père",
          "naissance": "Mère",
          "discipline": "Record",
          "pere": "2018",
          "mere": "Trot"
        },
        "course_actuelle": {
          "hippodrome": null,
          "nb_partants": 16,
          "allocation_eur": 59000,
          "distance_m": 2100,
          "vh": null
        },
        "cote_live_fiche": 2.1,
        "stats_couples": {
          "avec_jockey": {
            "nom": "F. NIVARD",
            "victoires": 1,
            "places": 7,
            "courses": 18,
            "pourcentage": 44.0
          },
          "avec_entraineur": {
            "nom": "D. HÉON",
            "victoires": 6,
            "places": 17,
            "courses": 71,
            "pourcentage": 32.0
          },
          "sur_hippodrome": {
            "nom": "PARIS-VINCENNES",
            "victoires": 1,
            "places": 4,
            "courses": 18,
            "pourcentage": 28.0
          }
        },
        "performances_globales": {
          "gains_eur": 193375,
          "musique": "Da Da 3a 3a 1a 1a (25) Da",
          "carriere": {
            "courses": 81,
            "victoires": 7,
            "places": 17,
            "pourcentage": 30.0
          }
        },
        "dernieres_courses": [],
        "derives": {
          "preference_terrain": null,
          "preference_distance": null,
          "jours_depuis_derniere_course": null
        }
      },
      "sous_scores": {
        "cote": 0.4337,
        "gains": 1.0,
        "couple_je": 0.38,
        "hippodrome": 0.28,
        "pref_terrain": 0.5,
        "pref_distance": 0.5,
        "recuperation": 0.5
      },
      "score": 50.85,
      "enrichi": true,
      "rang_predit": 1
    },
    {
      "numero": 1,
      "nom": "Idéal Dancer",
      "artifice": null,
      "sexe": "M",
      "age": 8,
      "poids": 2100.0,
      "jockey": "H. Monthulé",
      "musique": "5a(25)8a7a4a7a",
      "vh": null,
      "gains_eur": 188135,
      "entraineur": "S. Guarato",
      "cote_pmu": 10.0,
      "non_partant": false,
      "musique_raw": "5a(25)8a7a4a7a",
      "nb_courses_recentes": 5,
      "nb_victoires_recentes": 0,
      "nb_places_recentes": 0,
      "derniere_position": 5,
      "position_moyenne": 6.2,
      "sous_scores": {
        "cote": 0.0911,
        "gains": 0.9729,
        "couple_je": 0.5,
        "hippodrome": 0.5,
        "pref_terrain": 0.5,
        "pref_distance": 0.5,
        "recuperation": 0.5
      },
      "score": 40.74,
      "enrichi": false,
      "rang_predit": 2
    },
    {
      "numero": 5,
      "nom": "Faxima",
      "artifice": null,
      "sexe": "F",
      "age": 11,
      "poids": 2100.0,
      "jockey": "M. Abrivard",
      "musique": "4a3a6a7a5aDa",
      "vh": null,
      "gains_eur": 188920,
      "entraineur": "P. Julien",
      "cote_pmu": 16.0,
      "non_partant": false,
      "musique_raw": "4a3a6a7a5aDa",
      "nb_courses_recentes": 6,
      "nb_victoires_recentes": 0,
      "nb_places_recentes": 1,
      "derniere_position": 4,
      "position_moyenne": 5.0,
      "fiche_enrichie": {
        "numero": 5,
        "nom": "Faxima",
        "carte_identite": {
          "jockey": "Éleveur",
          "entraineur": "M. Abrivard",
          "proprietaire": "P. Julien",
          "eleveur": "P. Julien",
          "sexe": "Discipline",
          "robe": "Père",
          "naissance": "Mère",
          "discipline": "Record",
          "pere": "2015",
          "mere": "Trot"
        },
        "course_actuelle": {
          "hippodrome": null,
          "nb_partants": 16,
          "allocation_eur": 59000,
          "distance_m": 2100,
          "vh": null
        },
        "cote_live_fiche": 16.0,
        "stats_couples": {
          "avec_jockey": {
            "nom": "M. ABRIVARD",
            "victoires": 0,
            "places": 1,
            "courses": 1,
            "pourcentage": 100.0
          },
          "avec_entraineur": {
            "nom": "P. JULIEN",
            "victoires": 8,
            "places": 19,
            "courses": 74,
            "pourcentage": 36.0
          },
          "sur_hippodrome": {
            "nom": "PARIS-VINCENNES",
            "victoires": 0,
            "places": 1,
            "courses": 3,
            "pourcentage": 33.0
          }
        },
        "performances_globales": {
          "gains_eur": 188920,
          "musique": "4a 3a 6a 7a 5a Da (25) 5a",
          "carriere": {
            "courses": 74,
            "victoires": 8,
            "places": 19,
            "pourcentage": 36.0
          }
        },
        "dernieres_courses": [],
        "derives": {
          "preference_terrain": null,
          "preference_distance": null,
          "jours_depuis_derniere_course": null
        }
      },
      "sous_scores": {
        "cote": 0.0569,
        "gains": 0.977,
        "couple_je": 0.68,
        "hippodrome": 0.33,
        "pref_terrain": 0.5,
        "pref_distance": 0.5,
        "recuperation": 0.5
      },
      "score": 40.43,
      "enrichi": true,
      "rang_predit": 3
    },
    {
      "numero": 11,
      "nom": "Gitano Jack",
      "artifice": null,
      "sexe": "H",
      "age": 10,
      "poids": 2100.0,
      "jockey": "PP. Ploquin",
      "musique": "4a3a13a14a(25)Da",
      "vh": null,
      "gains_eur": 180500,
      "entraineur": "GM. Bernier",
      "cote_pmu": 12.0,
      "non_partant": false,
      "musique_raw": "4a3a13a14a(25)Da",
      "nb_courses_recentes": 5,
      "nb_victoires_recentes": 0,
      "nb_places_recentes": 2,
      "derniere_position": 4,
      "position_moyenne": 3.5,
      "fiche_enrichie": {
        "numero": 11,
        "nom": "Gitano Jack",
        "carte_identite": {
          "jockey": "Éleveur",
          "entraineur": "PP. Ploquin",
          "proprietaire": "GM. Bernier",
          "eleveur": "J. Grisanti",
          "sexe": "Discipline",
          "robe": "Père",
          "naissance": "Mère",
          "discipline": "Record",
          "pere": "2016",
          "mere": "Trot"
        },
        "course_actuelle": {
          "hippodrome": null,
          "nb_partants": 16,
          "allocation_eur": 59000,
          "distance_m": 2100,
          "vh": null
        },
        "cote_live_fiche": 12.0,
        "stats_couples": {
          "avec_jockey": {
            "nom": "PP. PLOQUIN",
            "victoires": 0,
            "places": 1,
            "courses": 2,
            "pourcentage": 50.0
          },
          "avec_entraineur": {
            "nom": "GM. BERNIER",
            "victoires": 0,
            "places": 5,
            "courses": 22,
            "pourcentage": 23.0
          },
          "sur_hippodrome": {
            "nom": "PARIS-VINCENNES",
            "victoires": 3,
            "places": 6,
            "courses": 20,
            "pourcentage": 45.0
          }
        },
        "performances_globales": {
          "gains_eur": 180500,
          "musique": "4a 3a 13a 14a (25) Da Da 13a",
          "carriere": {
            "courses": 65,
            "victoires": 7,
            "places": 17,
            "pourcentage": 37.0
          }
        },
        "dernieres_courses": [],
        "derives": {
          "preference_terrain": null,
          "preference_distance": null,
          "jours_depuis_derniere_course": null
        }
      },
      "sous_scores": {
        "cote": 0.0759,
        "gains": 0.9334,
        "couple_je": 0.365,
        "hippodrome": 0.45,
        "pref_terrain": 0.5,
        "pref_distance": 0.5,
        "recuperation": 0.5
      },
      "score": 37.01,
      "enrichi": true,
      "rang_predit": 4
    },
    {
      "numero": 16,
      "nom": "Hélali de Montceau",
      "artifice": null,
      "sexe": "F",
      "age": 9,
      "poids": 2100.0,
      "jockey": "GA. Pou Pou",
      "musique": "4a3a9aDa7a7a",
      "vh": null,
      "gains_eur": 161935,
      "entraineur": "GA. Pou Pou",
      "cote_pmu": 37.0,
      "non_partant": false,
      "musique_raw": "4a3a9aDa7a7a",
      "nb_courses_recentes": 6,
      "nb_victoires_recentes": 0,
      "nb_places_recentes": 1,
      "derniere_position": 4,
      "position_moyenne": 6.0,
      "sous_scores": {
        "cote": 0.0246,
        "gains": 0.8374,
        "couple_je": 0.5,
        "hippodrome": 0.5,
        "pref_terrain": 0.5,
        "pref_distance": 0.5,
        "recuperation": 0.5
      },
      "score": 36.05,
      "enrichi": false,
      "rang_predit": 5
    }
  ],
  "tous_chevaux": [
    {
      "numero": 4,
      "nom": "Idole Jallerie",
      "artifice": null,
      "sexe": "F",
      "age": 8,
      "poids": 2100.0,
      "jockey": "F. Nivard",
      "musique": "DaDa3a3a1a1a",
      "vh": null,
      "gains_eur": 193375,
      "entraineur": "D. Héon",
      "cote_pmu": 2.1,
      "non_partant": false,
      "musique_raw": "DaDa3a3a1a1a",
      "nb_courses_recentes": 6,
      "nb_victoires_recentes": 2,
      "nb_places_recentes": 4,
      "derniere_position": 3,
      "position_moyenne": 2.0,
      "fiche_enrichie": {
        "numero": 4,
        "nom": "Idole Jallerie",
        "carte_identite": {
          "jockey": "Éleveur",
          "entraineur": "F. Nivard",
          "proprietaire": "D. Héon",
          "eleveur": "D. Héon",
          "sexe": "Discipline",
          "robe": "Père",
          "naissance": "Mère",
          "discipline": "Record",
          "pere": "2018",
          "mere": "Trot"
        },
        "course_actuelle": {
          "hippodrome": null,
          "nb_partants": 16,
          "allocation_eur": 59000,
          "distance_m": 2100,
          "vh": null
        },
        "cote_live_fiche": 2.1,
        "stats_couples": {
          "avec_jockey": {
            "nom": "F. NIVARD",
            "victoires": 1,
            "places": 7,
            "courses": 18,
            "pourcentage": 44.0
          },
          "avec_entraineur": {
            "nom": "D. HÉON",
            "victoires": 6,
            "places": 17,
            "courses": 71,
            "pourcentage": 32.0
          },
          "sur_hippodrome": {
            "nom": "PARIS-VINCENNES",
            "victoires": 1,
            "places": 4,
            "courses": 18,
            "pourcentage": 28.0
          }
        },
        "performances_globales": {
          "gains_eur": 193375,
          "musique": "Da Da 3a 3a 1a 1a (25) Da",
          "carriere": {
            "courses": 81,
            "victoires": 7,
            "places": 17,
            "pourcentage": 30.0
          }
        },
        "dernieres_courses": [],
        "derives": {
          "preference_terrain": null,
          "preference_distance": null,
          "jours_depuis_derniere_course": null
        }
      },
      "sous_scores": {
        "cote": 0.4337,
        "gains": 1.0,
        "couple_je": 0.38,
        "hippodrome": 0.28,
        "pref_terrain": 0.5,
        "pref_distance": 0.5,
        "recuperation": 0.5
      },
      "score": 50.85,
      "enrichi": true,
      "rang_predit": 1
    },
    {
      "numero": 1,
      "nom": "Idéal Dancer",
      "artifice": null,
      "sexe": "M",
      "age": 8,
      "poids": 2100.0,
      "jockey": "H. Monthulé",
      "musique": "5a(25)8a7a4a7a",
      "vh": null,
      "gains_eur": 188135,
      "entraineur": "S. Guarato",
      "cote_pmu": 10.0,
      "non_partant": false,
      "musique_raw": "5a(25)8a7a4a7a",
      "nb_courses_recentes": 5,
      "nb_victoires_recentes": 0,
      "nb_places_recentes": 0,
      "derniere_position": 5,
      "position_moyenne": 6.2,
      "sous_scores": {
        "cote": 0.0911,
        "gains": 0.9729,
        "couple_je": 0.5,
        "hippodrome": 0.5,
        "pref_terrain": 0.5,
        "pref_distance": 0.5,
        "recuperation": 0.5
      },
      "score": 40.74,
      "enrichi": false,
      "rang_predit": 2
    },
    {
      "numero": 5,
      "nom": "Faxima",
      "artifice": null,
      "sexe": "F",
      "age": 11,
      "poids": 2100.0,
      "jockey": "M. Abrivard",
      "musique": "4a3a6a7a5aDa",
      "vh": null,
      "gains_eur": 188920,
      "entraineur": "P. Julien",
      "cote_pmu": 16.0,
      "non_partant": false,
      "musique_raw": "4a3a6a7a5aDa",
      "nb_courses_recentes": 6,
      "nb_victoires_recentes": 0,
      "nb_places_recentes": 1,
      "derniere_position": 4,
      "position_moyenne": 5.0,
      "fiche_enrichie": {
        "numero": 5,
        "nom": "Faxima",
        "carte_identite": {
          "jockey": "Éleveur",
          "entraineur": "M. Abrivard",
          "proprietaire": "P. Julien",
          "eleveur": "P. Julien",
          "sexe": "Discipline",
          "robe": "Père",
          "naissance": "Mère",
          "discipline": "Record",
          "pere": "2015",
          "mere": "Trot"
        },
        "course_actuelle": {
          "hippodrome": null,
          "nb_partants": 16,
          "allocation_eur": 59000,
          "distance_m": 2100,
          "vh": null
        },
        "cote_live_fiche": 16.0,
        "stats_couples": {
          "avec_jockey": {
            "nom": "M. ABRIVARD",
            "victoires": 0,
            "places": 1,
            "courses": 1,
            "pourcentage": 100.0
          },
          "avec_entraineur": {
            "nom": "P. JULIEN",
            "victoires": 8,
            "places": 19,
            "courses": 74,
            "pourcentage": 36.0
          },
          "sur_hippodrome": {
            "nom": "PARIS-VINCENNES",
            "victoires": 0,
            "places": 1,
            "courses": 3,
            "pourcentage": 33.0
          }
        },
        "performances_globales": {
          "gains_eur": 188920,
          "musique": "4a 3a 6a 7a 5a Da (25) 5a",
          "carriere": {
            "courses": 74,
            "victoires": 8,
            "places": 19,
            "pourcentage": 36.0
          }
        },
        "dernieres_courses": [],
        "derives": {
          "preference_terrain": null,
          "preference_distance": null,
          "jours_depuis_derniere_course": null
        }
      },
      "sous_scores": {
        "cote": 0.0569,
        "gains": 0.977,
        "couple_je": 0.68,
        "hippodrome": 0.33,
        "pref_terrain": 0.5,
        "pref_distance": 0.5,
        "recuperation": 0.5
      },
      "score": 40.43,
      "enrichi": true,
      "rang_predit": 3
    },
    {
      "numero": 11,
      "nom": "Gitano Jack",
      "artifice": null,
      "sexe": "H",
      "age": 10,
      "poids": 2100.0,
      "jockey": "PP. Ploquin",
      "musique": "4a3a13a14a(25)Da",
      "vh": null,
      "gains_eur": 180500,
      "entraineur": "GM. Bernier",
      "cote_pmu": 12.0,
      "non_partant": false,
      "musique_raw": "4a3a13a14a(25)Da",
      "nb_courses_recentes": 5,
      "nb_victoires_recentes": 0,
      "nb_places_recentes": 2,
      "derniere_position": 4,
      "position_moyenne": 3.5,
      "fiche_enrichie": {
        "numero": 11,
        "nom": "Gitano Jack",
        "carte_identite": {
          "jockey": "Éleveur",
          "entraineur": "PP. Ploquin",
          "proprietaire": "GM. Bernier",
          "eleveur": "J. Grisanti",
          "sexe": "Discipline",
          "robe": "Père",
          "naissance": "Mère",
          "discipline": "Record",
          "pere": "2016",
          "mere": "Trot"
        },
        "course_actuelle": {
          "hippodrome": null,
          "nb_partants": 16,
          "allocation_eur": 59000,
          "distance_m": 2100,
          "vh": null
        },
        "cote_live_fiche": 12.0,
        "stats_couples": {
          "avec_jockey": {
            "nom": "PP. PLOQUIN",
            "victoires": 0,
            "places": 1,
            "courses": 2,
            "pourcentage": 50.0
          },
          "avec_entraineur": {
            "nom": "GM. BERNIER",
            "victoires": 0,
            "places": 5,
            "courses": 22,
            "pourcentage": 23.0
          },
          "sur_hippodrome": {
            "nom": "PARIS-VINCENNES",
            "victoires": 3,
            "places": 6,
            "courses": 20,
            "pourcentage": 45.0
          }
        },
        "performances_globales": {
          "gains_eur": 180500,
          "musique": "4a 3a 13a 14a (25) Da Da 13a",
          "carriere": {
            "courses": 65,
            "victoires": 7,
            "places": 17,
            "pourcentage": 37.0
          }
        },
        "dernieres_courses": [],
        "derives": {
          "preference_terrain": null,
          "preference_distance": null,
          "jours_depuis_derniere_course": null
        }
      },
      "sous_scores": {
        "cote": 0.0759,
        "gains": 0.9334,
        "couple_je": 0.365,
        "hippodrome": 0.45,
        "pref_terrain": 0.5,
        "pref_distance": 0.5,
        "recuperation": 0.5
      },
      "score": 37.01,
      "enrichi": true,
      "rang_predit": 4
    },
    {
      "numero": 16,
      "nom": "Hélali de Montceau",
      "artifice": null,
      "sexe": "F",
      "age": 9,
      "poids": 2100.0,
      "jockey": "GA. Pou Pou",
      "musique": "4a3a9aDa7a7a",
      "vh": null,
      "gains_eur": 161935,
      "entraineur": "GA. Pou Pou",
      "cote_pmu": 37.0,
      "non_partant": false,
      "musique_raw": "4a3a9aDa7a7a",
      "nb_courses_recentes": 6,
      "nb_victoires_recentes": 0,
      "nb_places_recentes": 1,
      "derniere_position": 4,
      "position_moyenne": 6.0,
      "sous_scores": {
        "cote": 0.0246,
        "gains": 0.8374,
        "couple_je": 0.5,
        "hippodrome": 0.5,
        "pref_terrain": 0.5,
        "pref_distance": 0.5,
        "recuperation": 0.5
      },
      "score": 36.05,
      "enrichi": false,
      "rang_predit": 5
    },
    {
      "numero": 2,
      "nom": "Hipparis",
      "artifice": null,
      "sexe": "H",
      "age": 9,
      "poids": 2100.0,
      "jockey": "JF. Senet",
      "musique": "7a11a2a2a2a6a",
      "vh": null,
      "gains_eur": 190280,
      "entraineur": "JF. Senet",
      "cote_pmu": 16.0,
      "non_partant": false,
      "musique_raw": "7a11a2a2a2a6a",
      "nb_courses_recentes": 6,
      "nb_victoires_recentes": 1,
      "nb_places_recentes": 4,
      "derniere_position": 7,
      "position_moyenne": 3.33,
      "fiche_enrichie": {
        "numero": 2,
        "nom": "Hipparis",
        "carte_identite": {
          "jockey": "Éleveur",
          "entraineur": "JF. Senet",
          "proprietaire": "JF. Senet",
          "eleveur": "Ecurie J-François Senet",
          "sexe": "Discipline",
          "robe": "Père",
          "naissance": "Mère",
          "discipline": "Record",
          "pere": "2017",
          "mere": "Trot"
        },
        "course_actuelle": {
          "hippodrome": null,
          "nb_partants": 16,
          "allocation_eur": 59000,
          "distance_m": 2100,
          "vh": null
        },
        "cote_live_fiche": 16.0,
        "stats_couples": {
          "avec_jockey": {
            "nom": "JF. SENET",
            "victoires": 3,
            "places": 16,
            "courses": 50,
            "pourcentage": 38.0
          },
          "avec_entraineur": {
            "nom": "JF. SENET",
            "victoires": 6,
            "places": 23,
            "courses": 91,
            "pourcentage": 32.0
          },
          "sur_hippodrome": {
            "nom": "PARIS-VINCENNES",
            "victoires": 2,
            "places": 2,
            "courses": 15,
            "pourcentage": 27.0
          }
        },
        "performances_globales": {
          "gains_eur": 190280,
          "musique": "7a 11a 2a 2a 2a 6a 3a (25)",
          "carriere": {
            "courses": 93,
            "victoires": 6,
            "places": 23,
            "pourcentage": 31.0
          }
        },
        "dernieres_courses": [],
        "derives": {
          "preference_terrain": null,
          "preference_distance": null,
          "jours_depuis_derniere_course": null
        }
      },
      "sous_scores": {
        "cote": 0.0569,
        "gains": 0.984,
        "couple_je": 0.35,
        "hippodrome": 0.27,
        "pref_terrain": 0.5,
        "pref_distance": 0.5,
        "recuperation": 0.5
      },
      "score": 34.99,
      "enrichi": true,
      "rang_predit": 6
    },
    {
      "numero": 8,
      "nom": "Iquito Planchette",
      "artifice": null,
      "sexe": "H",
      "age": 8,
      "poids": 2100.0,
      "jockey": "F. Blandin",
      "musique": "Da1a8mDa5a(25)",
      "vh": null,
      "gains_eur": 188323,
      "entraineur": "F. Blandin",
      "cote_pmu": 58.0,
      "non_partant": false,
      "musique_raw": "Da1a8mDa5a(25)",
      "nb_courses_recentes": 5,
      "nb_victoires_recentes": 1,
      "nb_places_recentes": 1,
      "derniere_position": 1,
      "position_moyenne": 4.67,
      "fiche_enrichie": {
        "numero": 8,
        "nom": "Iquito Planchette",
        "carte_identite": {
          "jockey": "Éleveur",
          "entraineur": "F. Blandin",
          "proprietaire": "F. Blandin",
          "eleveur": "Ecurie Franck Blandin",
          "sexe": "Discipline",
          "robe": "Père",
          "naissance": "Mère",
          "discipline": "Record",
          "pere": "2018",
          "mere": "Trot"
        },
        "course_actuelle": {
          "hippodrome": null,
          "nb_partants": 16,
          "allocation_eur": 59000,
          "distance_m": 2100,
          "vh": null
        },
        "cote_live_fiche": 58.0,
        "stats_couples": {
          "avec_jockey": {
            "nom": "F. BLANDIN",
            "victoires": 3,
            "places": 9,
            "courses": 49,
            "pourcentage": 24.0
          },
          "avec_entraineur": {
            "nom": "F. BLANDIN",
            "victoires": 14,
            "places": 17,
            "courses": 85,
            "pourcentage": 36.0
          },
          "sur_hippodrome": {
            "nom": "PARIS-VINCENNES",
            "victoires": 5,
            "places": 5,
            "courses": 24,
            "pourcentage": 42.0
          }
        },
        "performances_globales": {
          "gains_eur": 188323,
          "musique": "Da 1a 8m Da 5a (25) 5a 2a",
          "carriere": {
            "courses": 98,
            "victoires": 15,
            "places": 17,
            "pourcentage": 33.0
          }
        },
        "dernieres_courses": [],
        "derives": {
          "preference_terrain": null,
          "preference_distance": null,
          "jours_depuis_derniere_course": null
        }
      },
      "sous_scores": {
        "cote": 0.0157,
        "gains": 0.9739,
        "couple_je": 0.3,
        "hippodrome": 0.42,
        "pref_terrain": 0.5,
        "pref_distance": 0.5,
        "recuperation": 0.5
      },
      "score": 33.94,
      "enrichi": true,
      "rang_predit": 7
    },
    {
      "numero": 7,
      "nom": "Izia de Mongival",
      "artifice": null,
      "sexe": "F",
      "age": 8,
      "poids": 2100.0,
      "jockey": "G. Gelormini",
      "musique": "7a6a5a7a(25)0a",
      "vh": null,
      "gains_eur": 183610,
      "entraineur": "G. Lizée",
      "cote_pmu": 23.0,
      "non_partant": false,
      "musique_raw": "7a6a5a7a(25)0a",
      "nb_courses_recentes": 5,
      "nb_victoires_recentes": 0,
      "nb_places_recentes": 1,
      "derniere_position": 7,
      "position_moyenne": 5.0,
      "fiche_enrichie": {
        "numero": 7,
        "nom": "Izia de Mongival",
        "carte_identite": {
          "jockey": "Éleveur",
          "entraineur": "G. Gelormini",
          "proprietaire": "G. Lizée",
          "eleveur": "L. Kaszluk",
          "sexe": "Discipline",
          "robe": "Père",
          "naissance": "Mère",
          "discipline": "Record",
          "pere": "2018",
          "mere": "Trot"
        },
        "course_actuelle": {
          "hippodrome": null,
          "nb_partants": 16,
          "allocation_eur": 59000,
          "distance_m": 2100,
          "vh": null
        },
        "cote_live_fiche": 23.0,
        "stats_couples": {
          "avec_jockey": {
            "nom": "G. GELORMINI",
            "victoires": 0,
            "places": 0,
            "courses": 1,
            "pourcentage": 0.0
          },
          "avec_entraineur": {
            "nom": "G. LIZÉE",
            "victoires": 9,
            "places": 11,
            "courses": 51,
            "pourcentage": 39.0
          },
          "sur_hippodrome": {
            "nom": "PARIS-VINCENNES",
            "victoires": 1,
            "places": 5,
            "courses": 12,
            "pourcentage": 50.0
          }
        },
        "performances_globales": {
          "gains_eur": 183610,
          "musique": "7a 6a 5a 7a (25) 0a 11a 12a",
          "carriere": {
            "courses": 53,
            "victoires": 9,
            "places": 11,
            "pourcentage": 38.0
          }
        },
        "dernieres_courses": [],
        "derives": {
          "preference_terrain": null,
          "preference_distance": null,
          "jours_depuis_derniere_course": null
        }
      },
      "sous_scores": {
        "cote": 0.0396,
        "gains": 0.9495,
        "couple_je": 0.195,
        "hippodrome": 0.5,
        "pref_terrain": 0.5,
        "pref_distance": 0.5,
        "recuperation": 0.5
      },
      "score": 33.75,
      "enrichi": true,
      "rang_predit": 8
    },
    {
      "numero": 13,
      "nom": "Ialko Jenilat",
      "artifice": "oui",
      "sexe": "H",
      "age": 8,
      "poids": 2100.0,
      "jockey": "A. Desmarres",
      "musique": "6a7a3a(25)1a3a",
      "vh": null,
      "gains_eur": 176285,
      "entraineur": "A. Desmarres",
      "cote_pmu": 33.0,
      "non_partant": false,
      "musique_raw": "6a7a3a(25)1a3a",
      "nb_courses_recentes": 5,
      "nb_victoires_recentes": 1,
      "nb_places_recentes": 3,
      "derniere_position": 6,
      "position_moyenne": 4.0,
      "fiche_enrichie": {
        "numero": 13,
        "nom": "Ialko Jenilat",
        "carte_identite": {
          "jockey": "Éleveur",
          "entraineur": "A. Desmarres",
          "proprietaire": "A. Desmarres",
          "eleveur": "A. Desmarres",
          "sexe": "Discipline",
          "robe": "Père",
          "naissance": "Mère",
          "discipline": "Record",
          "pere": "2018",
          "mere": "Trot"
        },
        "course_actuelle": {
          "hippodrome": null,
          "nb_partants": 16,
          "allocation_eur": 59000,
          "distance_m": 2100,
          "vh": null
        },
        "cote_live_fiche": 33.0,
        "stats_couples": {
          "avec_jockey": {
            "nom": "A. DESMARRES",
            "victoires": 9,
            "places": 18,
            "courses": 50,
            "pourcentage": 54.0
          },
          "avec_entraineur": {
            "nom": "A. DESMARRES",
            "victoires": 7,
            "places": 18,
            "courses": 46,
            "pourcentage": 54.0
          },
          "sur_hippodrome": {
            "nom": "PARIS-VINCENNES",
            "victoires": 0,
            "places": 0,
            "courses": 4,
            "pourcentage": 0.0
          }
        },
        "performances_globales": {
          "gains_eur": 176285,
          "musique": "6a 7a 3a (25) 1a 3a 2a 1a",
          "carriere": {
            "courses": 51,
            "victoires": 9,
            "places": 18,
            "pourcentage": 53.0
          }
        },
        "dernieres_courses": [],
        "derives": {
          "preference_terrain": null,
          "preference_distance": null,
          "jours_depuis_derniere_course": null
        }
      },
      "sous_scores": {
        "cote": 0.0276,
        "gains": 0.9116,
        "couple_je": 0.54,
        "hippodrome": 0.0,
        "pref_terrain": 0.5,
        "pref_distance": 0.5,
        "recuperation": 0.5
      },
      "score": 32.88,
      "enrichi": true,
      "rang_predit": 9
    },
    {
      "numero": 12,
      "nom": "Golzac de Rem",
      "artifice": null,
      "sexe": "H",
      "age": 10,
      "poids": 2100.0,
      "jockey": "B. Rochard",
      "musique": "2a2a3a13a(25)Dm",
      "vh": null,
      "gains_eur": 178020,
      "entraineur": "K. Busnel",
      "cote_pmu": 20.0,
      "non_partant": false,
      "musique_raw": "2a2a3a13a(25)Dm",
      "nb_courses_recentes": 5,
      "nb_victoires_recentes": 0,
      "nb_places_recentes": 4,
      "derniere_position": 2,
      "position_moyenne": 2.5,
      "fiche_enrichie": {
        "numero": 12,
        "nom": "Golzac de Rem",
        "carte_identite": {
          "jockey": "Éleveur",
          "entraineur": "B. Rochard",
          "proprietaire": "K. Busnel",
          "eleveur": "K. Busnel",
          "sexe": "Discipline",
          "robe": "Père",
          "naissance": "Mère",
          "discipline": "Record",
          "pere": "2016",
          "mere": "Trot"
        },
        "course_actuelle": {
          "hippodrome": null,
          "nb_partants": 16,
          "allocation_eur": 59000,
          "distance_m": 2100,
          "vh": null
        },
        "cote_live_fiche": 20.0,
        "stats_couples": {
          "avec_jockey": {
            "nom": "B. ROCHARD",
            "victoires": 0,
            "places": 0,
            "courses": 0,
            "pourcentage": null
          },
          "avec_entraineur": {
            "nom": "K. BUSNEL",
            "victoires": 0,
            "places": 7,
            "courses": 19,
            "pourcentage": 37.0
          },
          "sur_hippodrome": {
            "nom": "PARIS-VINCENNES",
            "victoires": 0,
            "places": 1,
            "courses": 7,
            "pourcentage": 14.0
          }
        },
        "performances_globales": {
          "gains_eur": 178020,
          "musique": "2a 2a 3a 13a (25) Dm 10m 7a",
          "carriere": {
            "courses": 111,
            "victoires": 7,
            "places": 24,
            "pourcentage": 28.0
          }
        },
        "dernieres_courses": [],
        "derives": {
          "preference_terrain": null,
          "preference_distance": null,
          "jours_depuis_derniere_course": null
        }
      },
      "sous_scores": {
        "cote": 0.0455,
        "gains": 0.9206,
        "couple_je": 0.37,
        "hippodrome": 0.14,
        "pref_terrain": 0.5,
        "pref_distance": 0.5,
        "recuperation": 0.5
      },
      "score": 32.58,
      "enrichi": true,
      "rang_predit": 10
    },
    {
      "numero": 6,
      "nom": "Heaven Star",
      "artifice": null,
      "sexe": "H",
      "age": 9,
      "poids": 2100.0,
      "jockey": "Y. Lebourgeois",
      "musique": "11aDa8a10a15a(25)",
      "vh": null,
      "gains_eur": 192710,
      "entraineur": "S. Ernault",
      "cote_pmu": 27.0,
      "non_partant": false,
      "musique_raw": "11aDa8a10a15a(25)",
      "nb_courses_recentes": 5,
      "nb_victoires_recentes": 1,
      "nb_places_recentes": 2,
      "derniere_position": 1,
      "position_moyenne": 3.5,
      "fiche_enrichie": {
        "numero": 6,
        "nom": "Heaven Star",
        "carte_identite": {
          "jockey": "Éleveur",
          "entraineur": "Y. Lebourgeois",
          "proprietaire": "S. Ernault",
          "eleveur": "Ecurie des Charmes",
          "sexe": "Discipline",
          "robe": "Père",
          "naissance": "Mère",
          "discipline": "Record",
          "pere": "2017",
          "mere": "Trot"
        },
        "course_actuelle": {
          "hippodrome": null,
          "nb_partants": 16,
          "allocation_eur": 59000,
          "distance_m": 2100,
          "vh": null
        },
        "cote_live_fiche": 27.0,
        "stats_couples": {
          "avec_jockey": {
            "nom": "Y. LEBOURGEOIS",
            "victoires": 0,
            "places": 0,
            "courses": 0,
            "pourcentage": null
          },
          "avec_entraineur": {
            "nom": "S. ERNAULT",
            "victoires": 14,
            "places": 11,
            "courses": 61,
            "pourcentage": 41.0
          },
          "sur_hippodrome": {
            "nom": "PARIS-VINCENNES",
            "victoires": 0,
            "places": 0,
            "courses": 4,
            "pourcentage": 0.0
          }
        },
        "performances_globales": {
          "gains_eur": 192710,
          "musique": "11a Da 8a 10a 15a (25) Da 6a",
          "carriere": {
            "courses": 64,
            "victoires": 14,
            "places": 11,
            "pourcentage": 40.0
          }
        },
        "dernieres_courses": [],
        "derives": {
          "preference_terrain": null,
          "preference_distance": null,
          "jours_depuis_derniere_course": null
        }
      },
      "sous_scores": {
        "cote": 0.0337,
        "gains": 0.9966,
        "couple_je": 0.41,
        "hippodrome": 0.0,
        "pref_terrain": 0.5,
        "pref_distance": 0.5,
        "recuperation": 0.5
      },
      "score": 32.45,
      "enrichi": true,
      "rang_predit": 11
    },
    {
      "numero": 9,
      "nom": "Hippocrate du Trio",
      "artifice": null,
      "sexe": "H",
      "age": 9,
      "poids": 2100.0,
      "jockey": "M. Legros",
      "musique": "5a9a13a(25)8a6a",
      "vh": null,
      "gains_eur": 189430,
      "entraineur": "B. Marie",
      "cote_pmu": 89.0,
      "non_partant": false,
      "musique_raw": "5a9a13a(25)8a6a",
      "nb_courses_recentes": 5,
      "nb_victoires_recentes": 0,
      "nb_places_recentes": 1,
      "derniere_position": 5,
      "position_moyenne": 6.2,
      "fiche_enrichie": {
        "numero": 9,
        "nom": "Hippocrate du Trio",
        "carte_identite": {
          "jockey": "Éleveur",
          "entraineur": "M. Legros",
          "proprietaire": "B. Marie",
          "eleveur": "T. Lejeune",
          "sexe": "Discipline",
          "robe": "Père",
          "naissance": "Mère",
          "discipline": "Record",
          "pere": "2017",
          "mere": "Trot"
        },
        "course_actuelle": {
          "hippodrome": null,
          "nb_partants": 16,
          "allocation_eur": 59000,
          "distance_m": 2100,
          "vh": null
        },
        "cote_live_fiche": 89.0,
        "stats_couples": {
          "avec_jockey": {
            "nom": "M. LEGROS",
            "victoires": 0,
            "places": 2,
            "courses": 10,
            "pourcentage": 20.0
          },
          "avec_entraineur": {
            "nom": "B. MARIE",
            "victoires": 12,
            "places": 12,
            "courses": 54,
            "pourcentage": 44.0
          },
          "sur_hippodrome": {
            "nom": "PARIS-VINCENNES",
            "victoires": 1,
            "places": 1,
            "courses": 11,
            "pourcentage": 18.0
          }
        },
        "performances_globales": {
          "gains_eur": 189430,
          "musique": "5a 9a 13a (25) 8a 6a 10a 12a",
          "carriere": {
            "courses": 59,
            "victoires": 14,
            "places": 12,
            "pourcentage": 44.0
          }
        },
        "dernieres_courses": [],
        "derives": {
          "preference_terrain": null,
          "preference_distance": null,
          "jours_depuis_derniere_course": null
        }
      },
      "sous_scores": {
        "cote": 0.0102,
        "gains": 0.9796,
        "couple_je": 0.32,
        "hippodrome": 0.18,
        "pref_terrain": 0.5,
        "pref_distance": 0.5,
        "recuperation": 0.5
      },
      "score": 31.7,
      "enrichi": true,
      "rang_predit": 12
    },
    {
      "numero": 14,
      "nom": "Iron Mijack",
      "artifice": "oui",
      "sexe": "H",
      "age": 8,
      "poids": 2100.0,
      "jockey": "K. Busnel",
      "musique": "Da10a4a14aDa9a",
      "vh": null,
      "gains_eur": 144515,
      "entraineur": "K. Busnel",
      "cote_pmu": 116.0,
      "non_partant": false,
      "musique_raw": "Da10a4a14aDa9a",
      "nb_courses_recentes": 6,
      "nb_victoires_recentes": 0,
      "nb_places_recentes": 1,
      "derniere_position": 0,
      "position_moyenne": 4.25,
      "fiche_enrichie": {
        "numero": 14,
        "nom": "Iron Mijack",
        "carte_identite": {
          "jockey": "Éleveur",
          "entraineur": "K. Busnel",
          "proprietaire": "K. Busnel",
          "eleveur": "K. Busnel",
          "sexe": "Discipline",
          "robe": "Père",
          "naissance": "Mère",
          "discipline": "Record",
          "pere": "2018",
          "mere": "Trot"
        },
        "course_actuelle": {
          "hippodrome": null,
          "nb_partants": 16,
          "allocation_eur": 59000,
          "distance_m": 2100,
          "vh": null
        },
        "cote_live_fiche": 116.0,
        "stats_couples": {
          "avec_jockey": {
            "nom": "K. BUSNEL",
            "victoires": 0,
            "places": 0,
            "courses": 0,
            "pourcentage": null
          },
          "avec_entraineur": {
            "nom": "K. BUSNEL",
            "victoires": 0,
            "places": 0,
            "courses": 0,
            "pourcentage": null
          },
          "sur_hippodrome": {
            "nom": "PARIS-VINCENNES",
            "victoires": 2,
            "places": 3,
            "courses": 22,
            "pourcentage": 23.0
          }
        },
        "performances_globales": {
          "gains_eur": 144515,
          "musique": "Da 10a 4a 14a Da 9a 5a (25)",
          "carriere": {
            "courses": 75,
            "victoires": 5,
            "places": 16,
            "pourcentage": 28.0
          }
        },
        "dernieres_courses": [],
        "derives": {
          "preference_terrain": null,
          "preference_distance": null,
          "jours_depuis_derniere_course": null
        }
      },
      "sous_scores": {
        "cote": 0.0079,
        "gains": 0.7473,
        "couple_je": 0.5,
        "hippodrome": 0.23,
        "pref_terrain": 0.5,
        "pref_distance": 0.5,
        "recuperation": 0.5
      },
      "score": 31.32,
      "enrichi": true,
      "rang_predit": 13
    },
    {
      "numero": 3,
      "nom": "Hiatus",
      "artifice": null,
      "sexe": "H",
      "age": 9,
      "poids": 2100.0,
      "jockey": "N. Bazire",
      "musique": "10a4a7a13a8a1a",
      "vh": null,
      "gains_eur": 190530,
      "entraineur": "B. Bourgoin",
      "cote_pmu": 31.0,
      "non_partant": false,
      "musique_raw": "10a4a7a13a8a1a",
      "nb_courses_recentes": 6,
      "nb_victoires_recentes": 1,
      "nb_places_recentes": 3,
      "derniere_position": 0,
      "position_moyenne": 3.83,
      "fiche_enrichie": {
        "numero": 3,
        "nom": "Hiatus",
        "carte_identite": {
          "jockey": "Éleveur",
          "entraineur": "N. Bazire",
          "proprietaire": "B. Bourgoin",
          "eleveur": "Ecurie L.B.Bourgoin",
          "sexe": "Discipline",
          "robe": "Père",
          "naissance": "Mère",
          "discipline": "Record",
          "pere": "2017",
          "mere": "Trot"
        },
        "course_actuelle": {
          "hippodrome": null,
          "nb_partants": 16,
          "allocation_eur": 59000,
          "distance_m": 2100,
          "vh": null
        },
        "cote_live_fiche": 31.0,
        "stats_couples": {
          "avec_jockey": {
            "nom": "N. BAZIRE",
            "victoires": 0,
            "places": 0,
            "courses": 4,
            "pourcentage": 0.0
          },
          "avec_entraineur": {
            "nom": "B. BOURGOIN",
            "victoires": 5,
            "places": 15,
            "courses": 110,
            "pourcentage": 18.0
          },
          "sur_hippodrome": {
            "nom": "PARIS-VINCENNES",
            "victoires": 3,
            "places": 8,
            "courses": 49,
            "pourcentage": 22.0
          }
        },
        "performances_globales": {
          "gains_eur": 190530,
          "musique": "10a 4a 7a 13a 8a 1a Dm (25)",
          "carriere": {
            "courses": 112,
            "victoires": 5,
            "places": 15,
            "pourcentage": 18.0
          }
        },
        "dernieres_courses": [],
        "derives": {
          "preference_terrain": null,
          "preference_distance": null,
          "jours_depuis_derniere_course": null
        }
      },
      "sous_scores": {
        "cote": 0.0294,
        "gains": 0.9853,
        "couple_je": 0.09,
        "hippodrome": 0.22,
        "pref_terrain": 0.5,
        "pref_distance": 0.5,
        "recuperation": 0.5
      },
      "score": 29.5,
      "enrichi": true,
      "rang_predit": 14
    },
    {
      "numero": 10,
      "nom": "Heraklion Desbois",
      "artifice": "oui",
      "sexe": "H",
      "age": 9,
      "poids": 2100.0,
      "jockey": "A. Gendrot",
      "musique": "5a4a6a9a7a(25)",
      "vh": null,
      "gains_eur": 182705,
      "entraineur": "P. Gendry",
      "cote_pmu": 40.0,
      "non_partant": false,
      "musique_raw": "5a4a6a9a7a(25)",
      "nb_courses_recentes": 5,
      "nb_victoires_recentes": 0,
      "nb_places_recentes": 0,
      "derniere_position": 5,
      "position_moyenne": 6.2,
      "fiche_enrichie": {
        "numero": 10,
        "nom": "Heraklion Desbois",
        "carte_identite": {
          "jockey": "Éleveur",
          "entraineur": "A. Gendrot",
          "proprietaire": "P. Gendry",
          "eleveur": "P. Gendry",
          "sexe": "Discipline",
          "robe": "Père",
          "naissance": "Mère",
          "discipline": "Record",
          "pere": "2017",
          "mere": "Trot"
        },
        "course_actuelle": {
          "hippodrome": null,
          "nb_partants": 16,
          "allocation_eur": 59000,
          "distance_m": 2100,
          "vh": null
        },
        "cote_live_fiche": 40.0,
        "stats_couples": {
          "avec_jockey": {
            "nom": "A. GENDROT",
            "victoires": 0,
            "places": 0,
            "courses": 2,
            "pourcentage": 0.0
          },
          "avec_entraineur": {
            "nom": "P. GENDRY",
            "victoires": 2,
            "places": 18,
            "courses": 141,
            "pourcentage": 14.0
          },
          "sur_hippodrome": {
            "nom": "PARIS-VINCENNES",
            "victoires": 1,
            "places": 4,
            "courses": 37,
            "pourcentage": 14.0
          }
        },
        "performances_globales": {
          "gains_eur": 182705,
          "musique": "5a 4a 6a 9a 7a (25) 3a 6a",
          "carriere": {
            "courses": 144,
            "victoires": 2,
            "places": 18,
            "pourcentage": 14.0
          }
        },
        "dernieres_courses": [],
        "derives": {
          "preference_terrain": null,
          "preference_distance": null,
          "jours_depuis_derniere_course": null
        }
      },
      "sous_scores": {
        "cote": 0.0228,
        "gains": 0.9448,
        "couple_je": 0.07,
        "hippodrome": 0.14,
        "pref_terrain": 0.5,
        "pref_distance": 0.5,
        "recuperation": 0.5
      },
      "score": 27.53,
      "enrichi": true,
      "rang_predit": 15
    },
    {
      "numero": 15,
      "nom": "Horse de Grammont",
      "artifice": null,
      "sexe": "H",
      "age": 9,
      "poids": 2100.0,
      "jockey": "J. Vanmeerbeck",
      "musique": "DaDaDa6a14a(25)",
      "vh": null,
      "gains_eur": 147610,
      "entraineur": "Jonathan Vanmeerbeck (s)",
      "cote_pmu": 32.0,
      "non_partant": false,
      "musique_raw": "DaDaDa6a14a(25)",
      "nb_courses_recentes": 5,
      "nb_victoires_recentes": 0,
      "nb_places_recentes": 0,
      "derniere_position": 6,
      "position_moyenne": 5.0,
      "fiche_enrichie": {
        "numero": 15,
        "nom": "Horse de Grammont",
        "carte_identite": {
          "jockey": "Éleveur",
          "entraineur": "J. Vanmeerbeck",
          "proprietaire": "Jonathan Vanmeerbeck (s)",
          "eleveur": "Mlle F. Auber",
          "sexe": "Discipline",
          "robe": "Père",
          "naissance": "Mère",
          "discipline": "Record",
          "pere": "2017",
          "mere": "Trot"
        },
        "course_actuelle": {
          "hippodrome": null,
          "nb_partants": 16,
          "allocation_eur": 59000,
          "distance_m": 2100,
          "vh": null
        },
        "cote_live_fiche": 32.0,
        "stats_couples": {
          "avec_jockey": {
            "nom": "J. VANMEERBECK",
            "victoires": 4,
            "places": 9,
            "courses": 52,
            "pourcentage": 25.0
          },
          "avec_entraineur": {
            "nom": "JONATHAN VANMEERBECK (S)",
            "victoires": 0,
            "places": 0,
            "courses": 5,
            "pourcentage": 0.0
          },
          "sur_hippodrome": {
            "nom": "PARIS-VINCENNES",
            "victoires": 2,
            "places": 0,
            "courses": 10,
            "pourcentage": 20.0
          }
        },
        "performances_globales": {
          "gains_eur": 147610,
          "musique": "Da Da Da 6a 14a (25) 5a 6a",
          "carriere": {
            "courses": 108,
            "victoires": 9,
            "places": 14,
            "pourcentage": 21.0
          }
        },
        "dernieres_courses": [],
        "derives": {
          "preference_terrain": null,
          "preference_distance": null,
          "jours_depuis_derniere_course": null
        }
      },
      "sous_scores": {
        "cote": 0.0285,
        "gains": 0.7633,
        "couple_je": 0.125,
        "hippodrome": 0.2,
        "pref_terrain": 0.5,
        "pref_distance": 0.5,
        "recuperation": 0.5
      },
      "score": 26.46,
      "enrichi": true,
      "rang_predit": 16
    }
  ],
  "nb_enrichis": 14,
  "nb_partants": 16,
  "cotes_dispo": 16
}